[
    {
        "title": "'They Should Be Ashamed': With Jobless Benefits to Expire in 9 Days, Republicans Pull Out All Stops to Obstruct Relief Bill | \"When Sen. Johnson voted to cut taxes for the wealthiest Americans, he didn't force staff to read the bill. But now that working people need help, he's forcing a delay.\"",
        "author": "theladynora",
        "url": "https://www.commondreams.org/news/2021/03/05/they-should-be-ashamed-jobless-benefits-expire-9-days-republicans-pull-out-all-stops"
    },
    {
        "title": "Meme People: Then and Now",
        "author": "hyp_0504",
        "url": "https://i.redd.it/tnhmeyrji7l61.jpg"
    },
    {
        "title": "What is a song you cannot listen to for an emotional reason?",
        "author": "missdundermifflin",
        "url": "https://www.reddit.com/r/AskReddit/comments/ly3972/what_is_a_song_you_cannot_listen_to_for_an/"
    },
    {
        "title": "The magical moment he realizes the hand belongs to friend not foe",
        "author": "9999monkeys",
        "url": "https://v.redd.it/3na0u4h3v6l61"
    },
    {
        "title": "WandaVision S01E09 - Discussion Thread",
        "author": "iliekpixels",
        "url": "https://www.reddit.com/r/marvelstudios/comments/ly72j0/wandavision_s01e09_discussion_thread/"
    },
    {
        "title": "GME Megathread for March 05, 2021",
        "author": "OPINION_IS_UNPOPULAR",
        "url": "https://www.reddit.com/r/wallstreetbets/comments/lybuq0/gme_megathread_for_march_05_2021/"
    },
    {
        "title": "The United States is now averaging 2 million vaccine doses administered per day.",
        "author": "rdmc23",
        "url": "https://www.nytimes.com/live/2021/03/04/world/covid-19-coronavirus/the-united-states-is-now-averaging-2-million-vaccine-doses-administered-per-day"
    },
    {
        "title": "What it’s like sleeping with a baby",
        "author": "jayson-",
        "url": "https://v.redd.it/8i7jl4bf66l61"
    },
    {
        "title": "Shade on a street in Jerez, Spain",
        "author": "Capital_Invite",
        "url": "https://i.redd.it/szbfsiz2x6l61.jpg"
    },
    {
        "title": "The ten years between 25 and 35 are far shorter than the four years between 14 and 18.",
        "author": "BandaidPuppet",
        "url": "https://www.reddit.com/r/Showerthoughts/comments/ly9rez/the_ten_years_between_25_and_35_are_far_shorter/"
    },
    {
        "title": "Public hospitals in Norway",
        "author": "neatlysanta",
        "url": "https://i.imgur.com/2MYxroT.gifv"
    },
    {
        "title": "LeBron: \"There's no slander to the Utah Jazz. You guys got to understand just like with video games growing up, we never played with Utah Jazz. Even as great as Karl Malone and John Stockton was, we never picked those guys .\"",
        "author": "suzukigun4life",
        "url": "https://streamable.com/5h351s"
    },
    {
        "title": "LPT: If someone slights/insults you publicly during a meeting, pretend like you didn't hear them the first time and politely ask them to repeat themself. They'll either double-down &amp; repeat the insult again, making them look rude &amp; unprofessional. Or they'll realize their mistake &amp; apologize to you.",
        "author": "brandonmcgritle",
        "url": "https://www.reddit.com/r/LifeProTips/comments/lxt9ld/lpt_if_someone_slightsinsults_you_publicly_during/"
    },
    {
        "title": "Apple tart coming out of the oven, this is a better one than my other photo",
        "author": "Stockholdsyndrome69",
        "url": "https://v.redd.it/b44ebfsx97l61"
    },
    {
        "title": "A gold mountain was discovered in Eastern DRC (South Kivu), reportedly the soil is 90% gold. Villagers are seen digging it up to bring it to their homes. (It is estimated that DRC contains $25 Trillion US dollars worth of natural resources).",
        "author": "mouthofreason",
        "url": "https://v.redd.it/cmvgzjx393l61"
    },
    {
        "title": "One Piece Chapter 1006",
        "author": "Kirosh",
        "url": "https://www.reddit.com/r/OnePiece/comments/ly78qf/one_piece_chapter_1006/"
    },
    {
        "title": "Picture of my mother in law walking the cows",
        "author": "mattykeights281",
        "url": "https://i.redd.it/lvome5wjy6l61.jpg"
    },
    {
        "title": "TIL that Ring was on Shark Tank and walked away without a deal. Ring later sold to Amazon for $1 billion.",
        "author": "HBombBrohan",
        "url": "https://www.youtube.com/watch?v=zcEDiOwv6Ro"
    },
    {
        "title": "What it’s like sleeping with a baby",
        "author": "yvesroyce2",
        "url": "https://v.redd.it/3yaj3c2un5l61"
    },
    {
        "title": "Pupper finds the water a little deeper than expected",
        "author": "one_loop",
        "url": "https://gfycat.com/unfortunatesizzlingboa"
    },
    {
        "title": "Bolsonaro tells Brazilians to ‘stop whining’ after record Covid-19 deaths",
        "author": "GTX1080SLI",
        "url": "https://www.france24.com/en/americas/20210305-bolsonaro-tells-brazilians-to-stop-whining-after-record-covid-19-deaths"
    },
    {
        "title": "We joke about older people not being able to use technology properly but their generations knew a ton of different skills that we don’t know how to do and would look equally dumb for.",
        "author": "McFlyLikeAnEagle",
        "url": "https://www.reddit.com/r/Showerthoughts/comments/ly242y/we_joke_about_older_people_not_being_able_to_use/"
    },
    {
        "title": "Misleading headline called out by Mom (edited cause got removed yesterday)",
        "author": "Dele10",
        "url": "https://i.redd.it/3owfyl18n2l61.jpg"
    },
    {
        "title": "They could have the house paid off in just 125 years.",
        "author": "headee",
        "url": "https://i.redd.it/11wcdsvlv6l61.jpg"
    },
    {
        "title": "what’s the cutest thing your girlfriend or wife does that the world should know about?",
        "author": "frozenolafff",
        "url": "https://www.reddit.com/r/AskMen/comments/ly54xz/whats_the_cutest_thing_your_girlfriend_or_wife/"
    }
]